{
	"description": "项目配置文件。",
	"packOptions": {
		"ignore": []
	},
	"setting": {
		"urlCheck": false,
		"es6": true,
		"postcss": true,
		"minified": true,
		"newFeature": true,
		"nodeModules": true,
		"autoAudits": false,
		"uglifyFileName": true,
		"checkInvalidKey": true,
		"checkSiteMap": true,
		"uploadWithSourceMap": true,
		"babelSetting": {
			"ignore": [],
			"disablePlugins": [],
			"outputPath": ""
		}
	},
	"compileType": "miniprogram",
	"libVersion": "2.10.4",
	"appid": "wx8a216ac4982d99d0",
	"projectname": "qs_budan",
	"isGameTourist": false,
	"simulatorType": "wechat",
	"simulatorPluginLibVersion": {},
	"condition": {
		"search": {
			"current": -1,
			"list": []
		},
		"conversation": {
			"current": -1,
			"list": []
		},
		"plugin": {
			"current": -1,
			"list": [
				{
					"id": -1,
					"name": "packageA/pages/home/home",
					"pathName": "packageA/pages/home/home",
					"query": "",
					"scene": null
				}
			]
		},
		"game": {
			"currentL": -1,
			"list": []
		},
		"gamePlugin": {
			"current": -1,
			"list": []
		},
		"miniprogram": {
			"current": -1,
			"list": [
				{
					"id": 0,
					"name": "pages/prepaid/prepaid",
					"pathName": "pages/prepaid/prepaid",
					"query": "orderId=632825681",
					"scene": null
				},
				{
					"id": -1,
					"name": "我的地址",
					"pathName": "pages/addrList/addrList",
					"query": "",
					"scene": null
				},
				{
					"id": 2,
					"name": "pages/control/control",
					"pathName": "pages/control/control",
					"query": "",
					"scene": null
				},
				{
					"id": 3,
					"name": "pages/comments/comments",
					"pathName": "pages/comments/comments",
					"query": "",
					"scene": null
				},
				{
					"id": 7,
					"name": "adver",
					"pathName": "pages/adver/adver",
					"query": "",
					"scene": null
				},
				{
					"id": 5,
					"name": "pages/comments/comments",
					"pathName": "pages/comments/comments",
					"query": "",
					"scene": null
				},
				{
					"id": -1,
					"name": "packageA/pages/home/home",
					"pathName": "packageA/pages/home/home",
					"query": "",
					"scene": null
				},
				{
					"id": -1,
					"name": "pageCode/pages/code/index",
					"pathName": "pageCode/pages/code/index",
					"query": "",
					"scene": null
				},
				{
					"id": 13,
					"name": "报名",
					"pathName": "pages/infoJoin/index",
					"query": "",
					"scene": 1011
				},
				{
					"id": 14,
					"name": "核销",
					"pathName": "pages/control/control",
					"query": "orderId=865501135",
					"scene": null
				},
				{
					"id": 10,
					"name": "二维码",
					"pathName": "pages/refund/refund",
					"query": "name=1",
					"scene": null
				},
				{
					"id": 11,
					"name": "pages/setAuth/setAuth",
					"pathName": "pages/setAuth/setAuth",
					"query": "scene=QSZ0443AAAA",
					"scene": null
				},
				{
					"id": -1,
					"name": "pages/refunedDesc/refunedDesc",
					"pathName": "pages/refunedDesc/refunedDesc",
					"query": "",
					"scene": null
				},
				{
					"id": 13,
					"name": "pages/finish/finish",
					"pathName": "pages/finish/finish",
					"query": "orderId=794721631",
					"scene": null
				},
				{
					"id": 14,
					"name": "pages/setRefun/setRefun",
					"pathName": "pages/setRefun/setRefun",
					"query": "scene=859513599",
					"scene": null
				},
				{
					"id": 15,
					"name": "pages/points/contract/contract",
					"pathName": "pages/points/contract/contract",
					"query": "scene=008440784",
					"scene": null
				}
			]
		}
	}
}